xarray_pickler/__init__.py
xarray_pickler/cli.py
xarray_pickler/config.py
xarray_pickler/xarray_pickler.py
xarray_pickler/etc/config.ini
xarray_pickler/etc/logging.conf
xarray_pickler-0.1.2.dist-info/AUTHORS.rst
xarray_pickler-0.1.2.dist-info/LICENSE
xarray_pickler-0.1.2.dist-info/METADATA
xarray_pickler-0.1.2.dist-info/WHEEL
xarray_pickler-0.1.2.dist-info/entry_points.txt
xarray_pickler-0.1.2.dist-info/top_level.txt
xarray_pickler-0.1.2.dist-info/RECORD
