Metadata-Version: 2.1
Name: xarray-pickler
Version: 0.1.2
Summary: Simple package to speed up 'multi-file open' operations for xarray datasets. Uses a cache of pickle files to store the metadata in the `xarray.Dataset` object.
Home-page: https://github.com/cedadev/xarray-pickler
Author: Elle Smith
Author-email: eleanor.smith@stfc.ac.uk
License: BSD - see LICENSE file in top-level package directory
Keywords: xarray_pickler
Platform: UNKNOWN
Classifier: Development Status :: 5 - Production/Stable
Classifier: Environment :: Console
Classifier: Environment :: Web Environment
Classifier: Intended Audience :: End Users/Desktop
Classifier: Intended Audience :: Developers
Classifier: Intended Audience :: System Administrators
Classifier: Intended Audience :: Science/Research
Classifier: License :: OSI Approved :: BSD License
Classifier: Natural Language :: English
Classifier: Operating System :: Microsoft :: Windows
Classifier: Operating System :: POSIX :: Linux
Classifier: Programming Language :: Python
Classifier: Programming Language :: Python :: 3
Classifier: Programming Language :: Python :: 3.5
Classifier: Programming Language :: Python :: 3.6
Classifier: Programming Language :: Python :: 3.7
Classifier: Programming Language :: Python :: 3.8
Classifier: Topic :: Security
Classifier: Topic :: Internet
Classifier: Topic :: Scientific/Engineering
Classifier: Topic :: System :: Distributed Computing
Classifier: Topic :: System :: Systems Administration :: Authentication/Directory
Classifier: Topic :: Software Development :: Libraries :: Python Modules
Requires-Python: >=3.6
License-File: LICENSE
License-File: AUTHORS.rst
Requires-Dist: cftime
Requires-Dist: xarray (>=0.15)
Requires-Dist: dask[complete] (>=2.6)
Requires-Dist: netCDF4 (>=1.4)
Provides-Extra: dev
Requires-Dist: pip ; extra == 'dev'
Requires-Dist: bump2version ; extra == 'dev'
Requires-Dist: wheel ; extra == 'dev'
Requires-Dist: watchdog ; extra == 'dev'
Requires-Dist: flake8 ; extra == 'dev'
Requires-Dist: tox ; extra == 'dev'
Requires-Dist: coverage ; extra == 'dev'
Requires-Dist: Sphinx ; extra == 'dev'
Requires-Dist: twine ; extra == 'dev'
Requires-Dist: pre-commit ; extra == 'dev'
Requires-Dist: GitPython ; extra == 'dev'
Requires-Dist: pytest ; extra == 'dev'
Requires-Dist: pytest-runner ; extra == 'dev'
Provides-Extra: docs
Requires-Dist: sphinx ; extra == 'docs'
Requires-Dist: sphinx-rtd-theme ; extra == 'docs'
Requires-Dist: nbsphinx ; extra == 'docs'
Requires-Dist: pandoc ; extra == 'docs'
Requires-Dist: ipython ; extra == 'docs'
Requires-Dist: ipykernel ; extra == 'docs'
Requires-Dist: jupyter-client ; extra == 'docs'
